adafruit_circuitpython_display_notification-1.0.6.dist-info/licenses/LICENSE
adafruit_display_notification/__init__.py
adafruit_display_notification/apple.py
adafruit_circuitpython_display_notification-1.0.6.dist-info/METADATA
adafruit_circuitpython_display_notification-1.0.6.dist-info/WHEEL
adafruit_circuitpython_display_notification-1.0.6.dist-info/top_level.txt
adafruit_circuitpython_display_notification-1.0.6.dist-info/RECORD
