Metadata-Version: 2.4
Name: adafruit-circuitpython-display-notification
Version: 1.0.6
Summary: Displayio Widgets for displaying notifications
Author-email: Adafruit Industries <circuitpython@adafruit.com>
License: MIT
Project-URL: Homepage, https://github.com/adafruit/Adafruit_CircuitPython_Display_Notification
Keywords: adafruit,blinka,circuitpython,micropython,display_notification,displayio,ble,ancs
Classifier: Intended Audience :: Developers
Classifier: Topic :: Software Development :: Libraries
Classifier: Topic :: Software Development :: Embedded Systems
Classifier: Topic :: System :: Hardware
Classifier: License :: OSI Approved :: MIT License
Classifier: Programming Language :: Python :: 3
License-File: LICENSE
Requires-Dist: Adafruit-Blinka
Requires-Dist: adafruit-circuitpython-display-text
Provides-Extra: optional
Dynamic: license-file
